README.md
setup.py
necessity/__init__.py
necessity/pd_dataframe.py
necessity/tc_sframe.py
necessity.egg-info/PKG-INFO
necessity.egg-info/SOURCES.txt
necessity.egg-info/dependency_links.txt
necessity.egg-info/requires.txt
necessity.egg-info/top_level.txt