Metadata-Version: 1.1
Name: necessity
Version: 0.0.11
Summary: Bear necessity
Home-page: https://github.com/alvations/necessity
Author: UNKNOWN
Author-email: UNKNOWN
License: UNKNOWN
Platform: UNKNOWN
Classifier: Programming Language :: Python :: 3
Classifier: License :: OSI Approved :: MIT License
Classifier: Operating System :: OS Independent
